our_custom_cli/__init__.py
our_custom_cli/cli.py
our_custom_cli-0.1.0.dist-info/METADATA
our_custom_cli-0.1.0.dist-info/WHEEL
our_custom_cli-0.1.0.dist-info/entry_points.txt
our_custom_cli-0.1.0.dist-info/RECORD
