Metadata-Version: 2.1
Name: our-custom-cli
Version: 0.1.0
Summary: 
Author: Charu Singh
Author-email: singh.c@northeastern.edu
Requires-Python: >=3.9,<4.0
Classifier: Programming Language :: Python :: 3
Classifier: Programming Language :: Python :: 3.9
Classifier: Programming Language :: Python :: 3.10
Classifier: Programming Language :: Python :: 3.11
Requires-Dist: typer[all] (>=0.7.0,<0.8.0)
